magvit2_pytorch/__init__.py
magvit2_pytorch/attend.py
magvit2_pytorch/data.py
magvit2_pytorch/magvit2_pytorch.py
magvit2_pytorch/optimizer.py
magvit2_pytorch/trainer.py
magvit2_pytorch/version.py
magvit2_pytorch-0.5.1.dist-info/LICENSE
magvit2_pytorch-0.5.1.dist-info/METADATA
magvit2_pytorch-0.5.1.dist-info/WHEEL
magvit2_pytorch-0.5.1.dist-info/top_level.txt
magvit2_pytorch-0.5.1.dist-info/RECORD
