Metadata-Version: 2.2
Name: magvit2-pytorch
Version: 0.5.1
Summary: MagViT2 - Pytorch
Home-page: https://github.com/lucidrains/magvit2-pytorch
Author: Phil Wang
Author-email: lucidrains@gmail.com
License: MIT
Keywords: artificial intelligence,deep learning,transformer,attention mechanisms,generative video model
Classifier: Development Status :: 4 - Beta
Classifier: Intended Audience :: Developers
Classifier: Topic :: Scientific/Engineering :: Artificial Intelligence
Classifier: License :: OSI Approved :: MIT License
Classifier: Programming Language :: Python :: 3.6
License-File: LICENSE
Requires-Dist: accelerate>=0.24.0
Requires-Dist: beartype
Requires-Dist: einops>=0.7.0
Requires-Dist: ema-pytorch>=0.2.4
Requires-Dist: pytorch-warmup
Requires-Dist: gateloop-transformer>=0.2.2
Requires-Dist: kornia
Requires-Dist: opencv-python
Requires-Dist: pillow
Requires-Dist: pytorch-custom-utils>=0.0.9
Requires-Dist: numpy
Requires-Dist: vector-quantize-pytorch>=1.14.39
Requires-Dist: taylor-series-linear-attention>=0.1.5
Requires-Dist: torch
Requires-Dist: torchvision
Requires-Dist: x-transformers
Dynamic: author
Dynamic: author-email
Dynamic: classifier
Dynamic: description-content-type
Dynamic: home-page
Dynamic: keywords
Dynamic: license
Dynamic: requires-dist
Dynamic: summary
